odoo/addons/account_invoice_margin_sale/README.rst
odoo/addons/account_invoice_margin_sale/__init__.py
odoo/addons/account_invoice_margin_sale/__manifest__.py
odoo/addons/account_invoice_margin_sale/i18n/account_invoice_margin_sale.pot
odoo/addons/account_invoice_margin_sale/i18n/es_PA.po
odoo/addons/account_invoice_margin_sale/i18n/it.po
odoo/addons/account_invoice_margin_sale/i18n/pt.po
odoo/addons/account_invoice_margin_sale/i18n/pt_BR.po
odoo/addons/account_invoice_margin_sale/models/__init__.py
odoo/addons/account_invoice_margin_sale/models/sale.py
odoo/addons/account_invoice_margin_sale/readme/CONTRIBUTORS.rst
odoo/addons/account_invoice_margin_sale/readme/DESCRIPTION.rst
odoo/addons/account_invoice_margin_sale/readme/INSTALL.rst
odoo/addons/account_invoice_margin_sale/static/description/icon.png
odoo/addons/account_invoice_margin_sale/static/description/index.html
odoo/addons/account_invoice_margin_sale/tests/__init__.py
odoo/addons/account_invoice_margin_sale/tests/test_account_invoice_margin_sale.py
odoo12_addon_account_invoice_margin_sale-12.0.1.0.0.99.dev11.dist-info/METADATA
odoo12_addon_account_invoice_margin_sale-12.0.1.0.0.99.dev11.dist-info/WHEEL
odoo12_addon_account_invoice_margin_sale-12.0.1.0.0.99.dev11.dist-info/top_level.txt
odoo12_addon_account_invoice_margin_sale-12.0.1.0.0.99.dev11.dist-info/RECORD
